investir/__init__.py
investir/cli.py
investir/config.py
investir/const.py
investir/exceptions.py
investir/fees.py
investir/logging.py
investir/output.py
investir/prettytable.py
investir/taxcalculator.py
investir/transaction.py
investir/trhistory.py
investir/typing.py
investir/utils.py
investir/findata/__init__.py
investir/findata/dataprovider.py
investir/findata/financialdata.py
investir/findata/hmrcprovider.py
investir/findata/localprovider.py
investir/findata/types.py
investir/findata/yahoofinanceprovider.py
investir/parser/__init__.py
investir/parser/factory.py
investir/parser/freetrade.py
investir/parser/trading212.py
investir/parser/types.py
investir-1.7.dist-info/LICENSE
investir-1.7.dist-info/METADATA
investir-1.7.dist-info/WHEEL
investir-1.7.dist-info/entry_points.txt
investir-1.7.dist-info/top_level.txt
investir-1.7.dist-info/RECORD
