Metadata-Version: 2.1
Name: investir
Version: 1.7
Summary: Calculate UK capital gains tax for Freetrade and Trading212
Author-email: Tiago Gomes <tiago.avv+oss@gmail.com>
Maintainer-email: Tiago Gomes <tiago.avv+oss@gmail.com>
License: MIT License
Project-URL: Homepage, https://github.com/tacgomes/investir
Project-URL: Repository, https://github.com/tacgomes/investir
Project-URL: Bug Tracker, https://github.com/tacgomes/investir/issues
Keywords: HMRC,Shares,Stock,Tax,Capital Gains,Freetrade,Trading212
Classifier: Development Status :: 5 - Production/Stable
Classifier: Environment :: Console
Classifier: Intended Audience :: End Users/Desktop
Classifier: License :: OSI Approved :: MIT License
Classifier: Natural Language :: English
Classifier: Operating System :: OS Independent
Classifier: Programming Language :: Python :: 3
Classifier: Programming Language :: Python :: 3 :: Only
Classifier: Programming Language :: Python :: 3.10
Classifier: Programming Language :: Python :: 3.11
Classifier: Programming Language :: Python :: 3.12
Classifier: Programming Language :: Python :: 3.13
Classifier: Programming Language :: Python :: 3.14
Classifier: Topic :: Office/Business
Classifier: Topic :: Office/Business :: Financial
Classifier: Topic :: Office/Business :: Financial :: Accounting
Classifier: Topic :: Office/Business :: Financial :: Investment
Classifier: Typing :: Typed
Requires-Python: >=3.10
License-File: LICENSE
Requires-Dist: click~=8.1.0
Requires-Dist: py-moneyed~=3.0
Requires-Dist: platformdirs~=4.2.0
Requires-Dist: prettytable~=3.10.0
Requires-Dist: python-dateutil~=2.9.0
Requires-Dist: PyYAML~=6.0.0
Requires-Dist: typer~=0.20.0
Requires-Dist: yfinance~=0.2.54
Provides-Extra: lint
Requires-Dist: mypy~=1.18.0; extra == "lint"
Requires-Dist: ruff~=0.14.0; extra == "lint"
Provides-Extra: test
Requires-Dist: pandas==2.2.3; extra == "test"
Requires-Dist: pytest~=8.1.0; extra == "test"
Requires-Dist: pytest-cov~=5.0.0; extra == "test"
Requires-Dist: pytest-mock~=3.14.0; extra == "test"
